LICENSE
docs/changelog.rst
docs/constants.rst
docs/index.rst
docs/objects.rst
docs/quickstart.rst
docs/records.rst
netsgiro/__init__.py
netsgiro/constants.py
netsgiro/converters.py
netsgiro/enums.py
netsgiro/objects.py
netsgiro/py.typed
netsgiro/records.py
netsgiro/utils.py
netsgiro/validators.py
references/AvtaleGiro systemspesifikasjon des2016.pdf
references/OCR giro - System manual.pdf
netsgiro-2.0.1.dist-info/LICENSE
netsgiro-2.0.1.dist-info/WHEEL
netsgiro-2.0.1.dist-info/METADATA
netsgiro-2.0.1.dist-info/RECORD
