Metadata-Version: 2.1
Name: netsgiro
Version: 2.0.1
Summary: File parsers for Nets AvtaleGiro and OCR Giro
Home-page: https://pypi.org/project/netsgiro/
License: Apache License, Version 2.0
Keywords: avtalegiro,ocr,giro
Author: Otovo AS
Author-email: jodal+netsgiro@otovo.com
Requires-Python: >=3.7
Classifier: Development Status :: 5 - Production/Stable
Classifier: Intended Audience :: Developers
Classifier: License :: OSI Approved :: Apache Software License
Classifier: License :: Other/Proprietary License
Classifier: Programming Language :: Python :: 3
Classifier: Programming Language :: Python :: 3.10
Classifier: Programming Language :: Python :: 3.7
Classifier: Programming Language :: Python :: 3.8
Classifier: Programming Language :: Python :: 3.9
Classifier: Typing :: Typed
Provides-Extra: holidays
Requires-Dist: attrs (>=17.4)
Requires-Dist: backports.zoneinfo (>=0.2.1,<0.3.0); python_version < "3.9"
Project-URL: Changelog, https://netsgiro.readthedocs.io/en/latest/changelog/
Project-URL: Docs, https://netsgiro.readthedocs.io/
Project-URL: Repository, https://github.com/otovo/python-netsgiro
